telegram_mcp/__init__.py
telegram_mcp-0.6.3.dist-info/METADATA
telegram_mcp-0.6.3.dist-info/WHEEL
telegram_mcp-0.6.3.dist-info/entry_points.txt
telegram_mcp-0.6.3.dist-info/RECORD
