Metadata-Version: 2.4
Name: telegram-mcp
Version: 0.6.3
Summary: MCP server for Telegram - lets AI agents communicate with users via Telegram
Author-email: Furkan Kucuk <furkankucuk.dev@gmail.com>
License-Expression: MIT
Keywords: agent,ai,bot,mcp,telegram
Requires-Python: >=3.10
Requires-Dist: httpx>=0.27.0
Requires-Dist: mcp>=1.8.0
